[
    {
        "type": "number", 
        "name": "sell_rate",
        "label": "Sell Rate",
        "min": 0,
        "max": 3,
        "maxW": "100%",
        "align":"center",
        "width": "100%",
        "default": 1.50,
        "precision": 2,
        "step": 0.05,
        "prefix": "",
        "suffix": "%"
    },
    {
        "type": "spacer",
        "value": 4,
        "divider": true
    },
    {
        "type": "number", "name": "monthly_ttv",
        "label": "Monthly TTV",
        "flow": "row",
        "min": 10000,
        "max": 1000000,
        "default": 10000,
        "precision": 0,
        "step": 10000,
        "prefix": "$",
        "suffix": ""
    },
    {
        "type": "number", "name": "atv",
        "label": "ATV",
        "min": 1,
        "max": 500,
        "default": 50,
        "flow": "row",
        "precision": 2,
        "step": 1,
        "prefix": "$",
        "suffix": ""
    },
    {
        "type": "spacer",
        "value": 4,
        "divider": true
    },
    {
        "type": "dropdown", "name": "terminal_number",
        "label": "Terminal Model",
        "width": "100%",
        "min": 0,
        "max": 2,
        "default": 0,
        "precision": 0,
        "step": 1,
        "prefix": "Terminal",
        "suffix": "",
        "values": ["Choose", "SF12", "P400"]
    },
    {
        "type": "number", 
        "name": "terminal_quantity",
        "label": "Quantity",
        "width": "50%",
        "min": 0,
        "max": 20,
        "default": 0,
        "precision": 0,
        "step": 1,
        "prefix": "",
        "suffix": ""
    },
    {
        "type": "value", 
        "width": "50%",
        "name": "terminal_cost",
        "label": "Terminal Cost",
        "prefix": "$",
        "suffix": ""
    },
    {
        "type": "spacer",
        "value": 4,
        "divider": true
    },
    {
        "type": "number", "name": "free_pos",
        "label": "Subsidised POS",
        "min": 0,
        "max": 1000,
        "default": 0,
        "width": "50%",
        "precision": 2,
        "step": 25,
        "prefix": "$",
        "suffix": ""
    },
    {
        "type": "number", "name": "free_ba",
        "label": "Subsidised BA+",
        "min": 0,
        "max": 1000,
        "default": 0,
        "width": "50%",
        "precision": 2,
        "step": 25,
        "prefix": "$",
        "suffix": ""
    },
    {
        "type": "number", "name": "free_myplace",
        "label": "Subsidised MyPlace",
        "min": 0,
        "max": 1000,
        "default": 0,
        "width": "50%",
        "precision": 2,
        "step": 25,
        "prefix": "$",
        "suffix": ""
    },
    {
        "type": "number", "name": "amex_percent",
        "label": "Amex Percentage",
        "min": 0,
        "width": "50%",
        "max": 25,
        "default": 5,
        "precision": 0,
        "step": 1,
        "prefix": "",
        "suffix": "%"
    }
    
]